LICENSE
MANIFEST.in
Makefile
README.md
requirements.txt
requirements_dev.txt
setup.py
BigQuery_GCS.egg-info/PKG-INFO
BigQuery_GCS.egg-info/SOURCES.txt
BigQuery_GCS.egg-info/dependency_links.txt
BigQuery_GCS.egg-info/requires.txt
BigQuery_GCS.egg-info/top_level.txt
bigquery_gcs/__init__.py
bigquery_gcs/base.py
bigquery_gcs/exceptions.py
bigquery_gcs/utils.py
tests/__init__.py
tests/test_base.py
tests/test_utils.py