Metadata-Version: 1.1
Name: BigQuery-GCS
Version: 0.0.7
Summary: Export Large Results from BigQuery to Google Cloud Storage
Home-page: https://github.com/pirsquare/BigQuery-GCS
Author: Ryan Liao
Author-email: pirsquare.ryan@gmail.com
License: MIT
Platform: UNKNOWN
Classifier: Development Status :: 4 - Beta
Classifier: Environment :: Web Environment
Classifier: Intended Audience :: Developers
Classifier: Operating System :: OS Independent
Classifier: Programming Language :: Python
